MANIFEST.in
setup.py
nucleon/__init__.py
nucleon/cache.py
nucleon/commands.py
nucleon/config.py
nucleon/framework.py
nucleon/http.py
nucleon/loader.py
nucleon/main.py
nucleon/signals.py
nucleon/tests.py
nucleon/util.py
nucleon/validation.py
nucleon.egg-info/PKG-INFO
nucleon.egg-info/SOURCES.txt
nucleon.egg-info/dependency_links.txt
nucleon.egg-info/entry_points.txt
nucleon.egg-info/namespace_packages.txt
nucleon.egg-info/requires.txt
nucleon.egg-info/top_level.txt
nucleon/database/__init__.py
nucleon/database/api.py
nucleon/database/management.py
nucleon/database/pgpool.py
nucleon/database/psyco_gevent.py
nucleon/skel/app.cfg
nucleon/skel/app.py
nucleon/skel/database.sql
nucleon/skel/tests.py