Metadata-Version: 1.1
Name: nucleon
Version: 0.1
Summary: A gevent-based microframework for building RESTful web services that provide AMQP interfaces.
Home-page: https://docs.vertulabs.co.uk/nucleon/
Author: Vertu Infrastructure Development Team
Author-email: ops@vertulabs.co.uk
License: UNKNOWN
Platform: UNKNOWN
Classifier: Development Status :: 4 - Beta
Classifier: Intended Audience :: Developers
Classifier: Operating System :: POSIX
Classifier: Programming Language :: Python :: 2
Classifier: License :: OSI Approved :: GNU Lesser General Public License v3 (LGPLv3)
Classifier: Topic :: Software Development :: Libraries :: Python Modules
